ConsoleHelp/__init__.py
ConsoleHelp/main.py
ConsoleHelp-0.5.0.dist-info/LICENSE 
ConsoleHelp-0.5.0.dist-info/METADATA
ConsoleHelp-0.5.0.dist-info/WHEEL
ConsoleHelp-0.5.0.dist-info/top_level.txt
ConsoleHelp-0.5.0.dist-info/zip-safe
ConsoleHelp-0.5.0.dist-info/RECORD
